pystreamdl.py
pystreamdl-0.0.2.dist-info/DESCRIPTION.rst
pystreamdl-0.0.2.dist-info/METADATA
pystreamdl-0.0.2.dist-info/RECORD
pystreamdl-0.0.2.dist-info/WHEEL
pystreamdl-0.0.2.dist-info/metadata.json
pystreamdl-0.0.2.dist-info/top_level.txt
